README.md
setup.py
cvra_packager/CMakeLists.txt.jinja
cvra_packager/Makefile.arm.jinja
cvra_packager/Makefile.base.jinja
cvra_packager/Makefile.x86.jinja
cvra_packager/__init__.py
cvra_packager/packager.py
cvra_packager/packager_to_bazel.py
cvra_packager.egg-info/PKG-INFO
cvra_packager.egg-info/SOURCES.txt
cvra_packager.egg-info/dependency_links.txt
cvra_packager.egg-info/entry_points.txt
cvra_packager.egg-info/requires.txt
cvra_packager.egg-info/top_level.txt