Metadata-Version: 1.1
Name: cvra-packager
Version: 1.2.0
Summary: CVRA packaging system
Home-page: https://github.com/cvra/packager
Author: Club Vaudois de Robotique Autonome
Author-email: info@cvra.ch
License: BSD
Platform: UNKNOWN
Classifier: Development Status :: 5 - Production/Stable
Classifier: Intended Audience :: Developers
Classifier: Topic :: Software Development :: Embedded Systems
Classifier: License :: OSI Approved :: BSD License
Classifier: Programming Language :: Python :: 3 :: Only
Classifier: Programming Language :: Python :: 3.4
Classifier: Programming Language :: Python :: 3.5
Classifier: Programming Language :: Python :: 3.6
